[
  {
    "severity": "P3",
    "type": "model_params",
    "file": "src/coach/agent.py",
    "detail": "BKT model: prior=0.3, guess=0.1, slip=0.1, learn=0.2 — verify against domain data"
  },
  {
    "severity": "P3",
    "type": "model_params",
    "file": "src/coach/diagnostic_engine.py",
    "detail": "BKT model: prior=0.3, guess=0.1, slip=0.1, learn=0.2 — verify against domain data"
  },
  {
    "severity": "P3",
    "type": "model_params",
    "file": "src/coach/flow.py",
    "detail": "BKT model: prior=0.3, guess=0.1, slip=0.1, learn=0.2 — verify against domain data"
  },
  {
    "severity": "P3",
    "type": "model_params",
    "file": "tests/test_exhaustive_quality.py",
    "detail": "BKT model: prior=0.3, guess=0.1, slip=0.1, learn=0.2 — verify against domain data"
  },
  {
    "severity": "P3",
    "type": "model_params",
    "file": "tests/test_flow.py",
    "detail": "BKT model: prior=0.3, guess=0.1, slip=0.1, learn=0.2 — verify against domain data"
  },
  {
    "severity": "P3",
    "type": "model_params",
    "file": "tests/test_phase23.py",
    "detail": "BKT model: prior=0.3, guess=0.1, slip=0.1, learn=0.2 — verify against domain data"
  }
]